pecuzal_embedding.py
pecuzal_embedding-1.3.4.data/data/data/lorenz_pecora_multi.csv
pecuzal_embedding-1.3.4.data/data/data/lorenz_pecora_uni_x.csv
pecuzal_embedding-1.3.4.data/data/data/roessler_test_series.csv
pecuzal_embedding-1.3.4.dist-info/LICENCE
pecuzal_embedding-1.3.4.dist-info/METADATA
pecuzal_embedding-1.3.4.dist-info/WHEEL
pecuzal_embedding-1.3.4.dist-info/top_level.txt
pecuzal_embedding-1.3.4.dist-info/RECORD
