Metadata-Version: 2.1
Name: pecuzal-embedding
Version: 1.3.4
Summary: PECUZAL automatic embedding of uni- and multivariate time series
Home-page: https://github.com/hkraemer/PECUZAL_python.git
Author: K.H.Kraemer
Author-email: hkraemer@pik-potsdam.de
License: UNKNOWN
Platform: UNKNOWN
Classifier: Programming Language :: Python :: 3.7
Classifier: Programming Language :: Python :: 3.8
Classifier: Intended Audience :: Science/Research
Classifier: Natural Language :: English
Classifier: Topic :: Scientific/Engineering :: GIS
Classifier: Topic :: Scientific/Engineering :: Mathematics
Classifier: Topic :: Scientific/Engineering :: Physics
Classifier: Topic :: Scientific/Engineering :: Information Analysis
Classifier: License :: OSI Approved :: MIT License
Classifier: Operating System :: OS Independent
Classifier: Development Status :: 5 - Production/Stable
Requires-Python: >=3.7
License-File: LICENCE
Requires-Dist: numpy (>=1.17.2)
Requires-Dist: scipy (<1.9,>=1.3.1)
Requires-Dist: scikit-learn (>=0.21.3)
Requires-Dist: progress (>=1.5)
